LICENSE
README.md
nautobot_ssot_aristacv/__init__.py
nautobot_ssot_aristacv/api/__init__.py
nautobot_ssot_aristacv/constant.py
nautobot_ssot_aristacv/diffsync/adapters/__init__.py
nautobot_ssot_aristacv/diffsync/adapters/cloudvision.py
nautobot_ssot_aristacv/diffsync/adapters/nautobot.py
nautobot_ssot_aristacv/diffsync/models/__init__.py
nautobot_ssot_aristacv/diffsync/models/base.py
nautobot_ssot_aristacv/diffsync/models/cloudvision.py
nautobot_ssot_aristacv/diffsync/models/nautobot.py
nautobot_ssot_aristacv/jobs.py
nautobot_ssot_aristacv/migrations/__init__.py
nautobot_ssot_aristacv/signals.py
nautobot_ssot_aristacv/static/nautobot_ssot_aristacv/cvp_logo.png
nautobot_ssot_aristacv/tests/__init__.py
nautobot_ssot_aristacv/tests/fixtures/__init__.py
nautobot_ssot_aristacv/tests/fixtures/fixtures.py
nautobot_ssot_aristacv/tests/fixtures/get_devices_response.json
nautobot_ssot_aristacv/tests/fixtures/get_interface_description_client_query.json
nautobot_ssot_aristacv/tests/fixtures/get_interface_mode_client_query_access.json
nautobot_ssot_aristacv/tests/fixtures/get_interface_mode_client_query_trunk.json
nautobot_ssot_aristacv/tests/fixtures/get_interface_transceiver_eeprom_client_query.json
nautobot_ssot_aristacv/tests/fixtures/get_interface_transceiver_local_client_query.json
nautobot_ssot_aristacv/tests/fixtures/get_interfaces_chassis_client_query.json
nautobot_ssot_aristacv/tests/fixtures/get_interfaces_chassis_response.json
nautobot_ssot_aristacv/tests/fixtures/get_interfaces_fixed_client_query.json
nautobot_ssot_aristacv/tests/fixtures/get_interfaces_fixed_response.json
nautobot_ssot_aristacv/tests/fixtures/get_ip_interfaces_client_query.json
nautobot_ssot_aristacv/tests/fixtures/get_ip_interfaces_response.json
nautobot_ssot_aristacv/tests/test_api.py
nautobot_ssot_aristacv/tests/test_basic.py
nautobot_ssot_aristacv/tests/test_cloudvision_adapter.py
nautobot_ssot_aristacv/tests/test_jobs.py
nautobot_ssot_aristacv/tests/test_nautobot_adapter.py
nautobot_ssot_aristacv-1.6.1.dist-info/LICENSE
nautobot_ssot_aristacv-1.6.1.dist-info/METADATA
nautobot_ssot_aristacv-1.6.1.dist-info/WHEEL
nautobot_ssot_aristacv-1.6.1.dist-info/RECORD
