Metadata-Version: 2.1
Name: nautobot-ssot-aristacv
Version: 1.6.1
Summary: Nautobot SSoT Arista CloudVision
Home-page: https://github.com/nautobot/nautobot-plugin-ssot-arista-cloudvision
License: Apache-2.0
Keywords: nautobot,nautobot-plugin
Author: Network to Code, LLC
Author-email: info@networktocode.com
Requires-Python: >=3.7,<4.0
Classifier: License :: OSI Approved :: Apache Software License
Classifier: Programming Language :: Python :: 3
Classifier: Programming Language :: Python :: 3.7
Classifier: Programming Language :: Python :: 3.8
Classifier: Programming Language :: Python :: 3.9
Classifier: Programming Language :: Python :: 3.10
Classifier: Programming Language :: Python :: 3.11
Provides-Extra: nautobot
Provides-Extra: nautobot-device-lifecycle-mgmt
Requires-Dist: cloudvision (>=1.9.0,<2.0.0)
Requires-Dist: cvprac (>=1.2.2,<2.0.0)
Requires-Dist: nautobot (>=1.4.0,<2.0.0) ; extra == "nautobot"
Requires-Dist: nautobot-ssot (==1.3.2)
Project-URL: Repository, https://github.com/nautobot/nautobot-plugin-ssot-arista-cloudvision
